bluetoof/__init__.py
bluetoof/core.py
bluetoof-0.2.0.dist-info/METADATA
bluetoof-0.2.0.dist-info/WHEEL
bluetoof-0.2.0.dist-info/top_level.txt
bluetoof-0.2.0.dist-info/RECORD
