Metadata-Version: 2.2
Name: bluetoof
Version: 0.2.0
Summary: Librairie Python pour interagir avec des appareils Bluetooth
Author: mz4r
Author-email: mz4r <mz4rr@proton.me>
License: MIT
Project-URL: Homepage, https://github.com/mz4r/bluetoof
Project-URL: Repository, https://github.com/mz4r/bluetoof
Dynamic: author
